{
  "$schema": "https://developer.microsoft.com/json-schemas/fabric/item/report/definition/visualContainer/2.10.0/schema.json",
  "name": "126b95b5c11b1d104960",
  "position": {
    "x": 58.358662613981764,
    "y": 453.25227963525839,
    "z": 5000,
    "height": 280.1215805471125,
    "width": 558.29787234042556,
    "tabOrder": 5000
  },
  "visual": {
    "visualType": "clusteredColumnChart",
    "query": {
      "queryState": {
        "Category": {
          "projections": [
            {
              "field": {
                "Column": {
                  "Expression": {
                    "SourceRef": {
                      "Entity": "trips_clean"
                    }
                  },
                  "Property": "hour_of_day"
                }
              },
              "queryRef": "trips_clean.hour_of_day",
              "nativeQueryRef": "hour_of_day",
              "active": true
            }
          ]
        },
        "Series": {
          "projections": [
            {
              "field": {
                "Column": {
                  "Expression": {
                    "SourceRef": {
                      "Entity": "trips_clean"
                    }
                  },
                  "Property": "airport_trip"
                }
              },
              "queryRef": "trips_clean.airport_trip",
              "nativeQueryRef": "airport_trip"
            }
          ]
        },
        "Y": {
          "projections": [
            {
              "field": {
                "Measure": {
                  "Expression": {
                    "SourceRef": {
                      "Entity": "trips_clean"
                    }
                  },
                  "Property": "Average Profit Per Hour"
                }
              },
              "queryRef": "trips_clean.Average Profit Per Hour",
              "nativeQueryRef": "Average Profit Per Hour"
            }
          ]
        }
      },
      "sortDefinition": {
        "sort": [
          {
            "field": {
              "Measure": {
                "Expression": {
                  "SourceRef": {
                    "Entity": "trips_clean"
                  }
                },
                "Property": "Average Profit Per Hour"
              }
            },
            "direction": "Descending"
          }
        ],
        "isDefaultSort": true
      }
    },
    "visualContainerObjects": {
      "title": [
        {
          "properties": {
            "text": {
              "expr": {
                "Literal": {
                  "Value": "'Airport Profitability by Hour'"
                }
              }
            }
          }
        }
      ]
    },
    "drillFilterOtherVisuals": true
  }
}